PBDD/include/BDD.py
PBDD/include/BDD_ite.py
PBDD/include/dot_bdd.py
PBL/include/PyBool_algorithms.py
PBL/include/PyBool_builder.py
PBL/include/PyBool_dimacs_parse.py
PBL/include/PyBool_public_interface.py
PBL/include/PyBool_std_parse.py
mcdc_checker/__init__.py
mcdc_checker/__main__.py
mcdc_checker/helper.py
mcdc_checker/report.py
mcdc_checker/tests/__init__.py
mcdc_checker/tests/main.c
mcdc_checker/tests/main.c.json
mcdc_checker/tests/test.h
mcdc_checker/tests/test_mcdc_checker.py
mcdc_checker/tree_checker.py
mcdc_checker-1.5.0.dist-info/LICENSE
mcdc_checker-1.5.0.dist-info/METADATA
mcdc_checker-1.5.0.dist-info/WHEEL
mcdc_checker-1.5.0.dist-info/entry_points.txt
mcdc_checker-1.5.0.dist-info/RECORD
